sextant/__init__.py
sextant/cli.py
sextant/dependency.py
sextant/module.py
sextant/scaffold.py
sextant/semver.py
tests/__init__.py
tests/test_cli.py
tests/test_dependency.py
tests/test_module.py
tests/test_package.py
tests/test_scaffold.py
sextant-0.5.0.dist-info/LICENSE
sextant-0.5.0.dist-info/METADATA
sextant-0.5.0.dist-info/WHEEL
sextant-0.5.0.dist-info/entry_points.txt
sextant-0.5.0.dist-info/top_level.txt
sextant-0.5.0.dist-info/RECORD
